come_again_question_mark/__init__.py
come_again_question_mark/__main__.py
come_again_question_mark/main.py
come_again_question_mark-0.1.8.dist-info/LICENSE
come_again_question_mark-0.1.8.dist-info/WHEEL
come_again_question_mark-0.1.8.dist-info/METADATA
come_again_question_mark-0.1.8.dist-info/RECORD
